lazyMossAPI/MossFrpAPI.py
lazyMossAPI/__init__.py
lazyMossAPI-0.0.1.dist-info/LICENSE
lazyMossAPI-0.0.1.dist-info/METADATA
lazyMossAPI-0.0.1.dist-info/WHEEL
lazyMossAPI-0.0.1.dist-info/top_level.txt
lazyMossAPI-0.0.1.dist-info/RECORD
