Metadata-Version: 2.1
Name: lazyMossAPI
Version: 0.0.1
Summary: 一个简单的用于请求MossFrp API的库
Author: MojaveHao
Author-email: HTTcode2020@126.com
License: AGPLv3
Classifier: Programming Language :: Python :: 3
Classifier: License :: OSI Approved :: GNU Affero General Public License v3 or later (AGPLv3+)
Classifier: Operating System :: OS Independent
Requires-Python: >3.6
License-File: LICENSE
Requires-Dist: requests
